{
  "cookies": [
    {
      "name": "relay-session",
      "value": "c9464f570551c9bdbe2b7a65587cebe1c826b8a582cef0f2a898b368fd3eb0b9",
      "domain": "localhost",
      "path": "/",
      "expires": 1781697381.075894,
      "httpOnly": true,
      "secure": false,
      "sameSite": "Lax"
    }
  ],
  "origins": [
    {
      "origin": "http://localhost:3033",
      "localStorage": [
        {
          "name": "relay-session-token",
          "value": "c9464f570551c9bdbe2b7a65587cebe1c826b8a582cef0f2a898b368fd3eb0b9"
        }
      ]
    }
  ]
}